fd_gcp/__init__.py
fd_gcp/_http.py
fd_gcp/auth.py
fd_gcp/common.py
fd_gcp/constants.py
fd_gcp/exceptions.py
fd_gcp/gcp_kms.py
fd_gcp/gcp_kms_mock.py
fd_gcp/py.typed
fyndata_gcp_utils-0.1.4.dist-info/LICENSE
fyndata_gcp_utils-0.1.4.dist-info/METADATA
fyndata_gcp_utils-0.1.4.dist-info/WHEEL
fyndata_gcp_utils-0.1.4.dist-info/top_level.txt
fyndata_gcp_utils-0.1.4.dist-info/RECORD
