Metadata-Version: 2.1
Name: fyndata-gcp-utils
Version: 0.1.4
Summary: Fyndata's Python library of Google Cloud Platform (GCP) utils.
Home-page: https://github.com/fyndata/gcp-utils-python
Author: Fyndata (Fynpal SpA)
Author-email: no-reply@fyndata.com
License: MIT
Platform: UNKNOWN
Classifier: Intended Audience :: Developers
Classifier: License :: OSI Approved :: MIT License
Classifier: Natural Language :: English
Classifier: Programming Language :: Python :: 3.7
Classifier: Programming Language :: Python :: 3.8
Requires-Python: >=3.7, <3.9
Requires-Dist: cryptography (>=2.7)
Requires-Dist: google-api-python-client (>=1.7.9)
Requires-Dist: google-auth (>=1.6.3)
Requires-Dist: requests (>=2.22.0)
